tensorkube/__init__.py
tensorkube/constants.py
tensorkube/helpers.py
tensorkube/tensorkube_token_server.py
tensorkube/configurations/base_cluster.yaml
tensorkube/configurations/bottlerocket_nodegroup.yaml
tensorkube/configurations/configuration_urls.py
tensorkube/configurations/karpenter_ec2nodeclass.yaml
tensorkube/configurations/karpenter_gpu_v1_ec2nodeclass.yaml
tensorkube/configurations/karpenter_gpu_v1_nodepool.yaml
tensorkube/configurations/karpenter_nodepool.yaml
tensorkube/configurations/karpenter_nodepool_deploy.yaml
tensorkube/configurations/migration_configmap.yaml
tensorkube/configurations/aws_configs/aws_efs_csi_driver_trust_policy.json
tensorkube/configurations/aws_configs/aws_s3_csi_driver_trust_policy.json
tensorkube/configurations/aws_configs/base_policy.json
tensorkube/configurations/aws_configs/dynamo_access_policy.json
tensorkube/configurations/aws_configs/ecr_repo_lifecycle_policy.json
tensorkube/configurations/aws_configs/eks_access_policy.json
tensorkube/configurations/aws_configs/iam_role_cluster_access_trust_policy.json
tensorkube/configurations/aws_configs/karpenter_controller_policy_v1.json
tensorkube/configurations/aws_configs/mountpoint_policy.json
tensorkube/configurations/aws_configs/s3_access_policy.json
tensorkube/configurations/aws_configs/sqs_access_policy.json
tensorkube/configurations/aws_configs/user_dynamo_access_policy.json
tensorkube/configurations/aws_configs/user_s3_access_policy.json
tensorkube/configurations/aws_configs/user_sqs_access_policy.json
tensorkube/configurations/axolotl_configs/gemma-3-27b-it.yaml
tensorkube/configurations/axolotl_configs/llama-3.1-70B-Instruct.yaml
tensorkube/configurations/axolotl_configs/llama-3.1-8B-Instruct.yaml
tensorkube/configurations/axolotl_configs/multi_gpu.yaml
tensorkube/configurations/axolotl_configs/single_gpu.yaml
tensorkube/configurations/build_configs/axolotl-train.yaml
tensorkube/configurations/build_configs/buildkit.yaml
tensorkube-0.1.6.dist-info/METADATA
tensorkube-0.1.6.dist-info/WHEEL
tensorkube-0.1.6.dist-info/entry_points.txt
tensorkube-0.1.6.dist-info/licenses/LICENSE
tensorkube-0.1.6.dist-info/RECORD
