Metadata-Version: 2.4
Name: tensorkube
Version: 0.1.6
Summary: Python SDK for Tensorfuse
Author-email: Samagra <samagra14@tensorfuse.io>, Divyanshu <divyanshu@tensorfuse.io>, Ganesh <ganesh@tensorfuse.io>
License-File: LICENSE
Classifier: License :: OSI Approved :: MIT License
Classifier: Operating System :: OS Independent
Classifier: Programming Language :: Python :: 3
Requires-Python: >=3.7
Requires-Dist: boto3==1.34.114
Requires-Dist: cfnresponse
Requires-Dist: click==8.1.7
Requires-Dist: inquirer==3.3.0
Requires-Dist: kubernetes==31.0.0
Requires-Dist: metapod==0.1.16
Requires-Dist: pathspec==0.12.1
Requires-Dist: requests==2.32.4
Requires-Dist: rich==13.7.1
Requires-Dist: semver==3.0.2
Requires-Dist: setuptools==78.1.1
Requires-Dist: tqdm==4.66.4
